textual_snowfall/__about__.py
textual_snowfall/__init__.py
textual_snowfall/__main__.py
textual_snowfall/stopwatch.py
textual_snowfall/stopwatch.tcss
textual_snowfall/widgets.py
textual_snowfall-0.0.3.post2.dist-info/METADATA
textual_snowfall-0.0.3.post2.dist-info/WHEEL
textual_snowfall-0.0.3.post2.dist-info/licenses/LICENSE.txt
textual_snowfall-0.0.3.post2.dist-info/RECORD
