Metadata-Version: 2.1
Name: textual-snowfall
Version: 0.0.3.post2
Project-URL: Documentation, https://github.com/lllama/textual-snowfall#readme
Project-URL: Issues, https://github.com/lllama/textual-snowfall/issues
Project-URL: Source, https://github.com/lllama/textual-snowfall
Author-email: Felix Ingram <f.ingram@gmail.com>
License-Expression: MIT
License-File: LICENSE.txt
Classifier: Development Status :: 4 - Beta
Classifier: Programming Language :: Python
Classifier: Programming Language :: Python :: 3.7
Classifier: Programming Language :: Python :: 3.8
Classifier: Programming Language :: Python :: 3.9
Classifier: Programming Language :: Python :: 3.10
Classifier: Programming Language :: Python :: 3.11
Classifier: Programming Language :: Python :: 3.12
Classifier: Programming Language :: Python :: Implementation :: CPython
Classifier: Programming Language :: Python :: Implementation :: PyPy
Requires-Python: >=3.7
Requires-Dist: textual
